{"name": "SE", "duration": 1244, "wave": {"id": 60, "simd": 3, "slot": 4, "begin": 265420, "end": 266664, "info": {"Issue": 20, "Valu": 5, "Valu_stall": 0, "Salu": 10, "Salu_stall": 2, "Vmem": 0, "Vmem_stall": 0, "Smem": 1, "Smem_stall": 0, "Flat": 1, "Flat_stall": 1, "Lds": 0, "Lds_stall": 0, "Br": 2, "Br_stall": 0, "Issue_stall": 0}, "instructions": [[265448, 1, 0, 4, 2], [265452, 2, 0, 4, 3], [265456, 2, 0, 4, 4], [265460, 9, 0, 48, 5], [265512, 2, 0, 4, 6], [265516, 2, 0, 4, 7], [265524, 8, 0, 4, 8], [265544, 2, 0, 72, 9], [265620, 2, 0, 4, 10], [265628, 2, 0, 4, 11], [265632, 2, 0, 4, 12], [265636, 6, 0, 4, 13], [265640, 6, 0, 4, 14], [265644, 6, 0, 4, 15], [265648, 6, 0, 4, 16], [265652, 6, 0, 4, 17], [265664, 4, 0, 208, 18], [265876, 2, 0, 4, 19], [265880, 2, 0, 4, 20], [265888, 7, 0, 4, 21]], "timeline": [[1, 28], [2, 12], [3, 48], [2, 36], [4, 68], [2, 8], [4, 8], [2, 36], [4, 208], [2, 788], [1, 4]], "waitcnt": [[5, [[2, 0]]]]}, "loop_count": {}, "top_n": [], "num_stitched": 20, "num_insts": 20, "websocket_port": 18000, "generation_time": "Wed May 28 09:55:56 2025"}