{"name": "SE", "duration": 928, "wave": {"id": 57, "simd": 3, "slot": 1, "begin": 264428, "end": 265356, "info": {"Issue": 20, "Valu": 5, "Valu_stall": 0, "Salu": 10, "Salu_stall": 1, "Vmem": 0, "Vmem_stall": 0, "Smem": 1, "Smem_stall": 0, "Flat": 1, "Flat_stall": 1, "Lds": 0, "Lds_stall": 0, "Br": 2, "Br_stall": 0, "Issue_stall": 0}, "instructions": [[264592, 1, 0, 4, 2], [264596, 2, 0, 4, 3], [264600, 2, 0, 4, 4], [264604, 9, 0, 108, 5], [264716, 2, 0, 4, 6], [264720, 2, 0, 4, 7], [264728, 8, 0, 4, 8], [264748, 2, 0, 12, 9], [264760, 2, 0, 4, 10], [264764, 2, 0, 4, 11], [264768, 2, 0, 4, 12], [264772, 6, 0, 4, 13], [264776, 6, 0, 4, 14], [264780, 6, 0, 4, 15], [264784, 6, 0, 4, 16], [264788, 6, 0, 4, 17], [264800, 4, 0, 96, 18], [264900, 2, 0, 4, 19], [264904, 2, 0, 4, 20], [264912, 7, 0, 4, 21]], "timeline": [[1, 164], [2, 12], [3, 108], [2, 36], [4, 8], [2, 44], [4, 96], [2, 456], [1, 4]], "waitcnt": [[5, [[2, 0]]]]}, "loop_count": {}, "top_n": [], "num_stitched": 20, "num_insts": 20, "websocket_port": 18000, "generation_time": "Wed May 28 09:55:56 2025"}