{"name": "SE", "duration": 944, "wave": {"id": 48, "simd": 2, "slot": 5, "begin": 265484, "end": 266428, "info": {"Issue": 20, "Valu": 5, "Valu_stall": 0, "Salu": 10, "Salu_stall": 0, "Vmem": 0, "Vmem_stall": 0, "Smem": 1, "Smem_stall": 1, "Flat": 1, "Flat_stall": 1, "Lds": 0, "Lds_stall": 0, "Br": 2, "Br_stall": 0, "Issue_stall": 0}, "instructions": [[265512, 1, 0, 12, 2], [265524, 2, 0, 4, 3], [265528, 2, 0, 4, 4], [265532, 9, 0, 24, 5], [265560, 2, 0, 4, 6], [265564, 2, 0, 4, 7], [265572, 8, 0, 4, 8], [265592, 2, 0, 4, 9], [265596, 2, 0, 4, 10], [265600, 2, 0, 4, 11], [265604, 2, 0, 4, 12], [265608, 6, 0, 4, 13], [265612, 6, 0, 4, 14], [265616, 6, 0, 4, 15], [265620, 6, 0, 4, 16], [265624, 6, 0, 4, 17], [265636, 4, 0, 28, 18], [265668, 2, 0, 4, 19], [265672, 2, 0, 4, 20], [265680, 7, 0, 4, 21]], "timeline": [[1, 28], [4, 8], [2, 12], [3, 24], [2, 80], [4, 28], [2, 764]], "waitcnt": [[5, [[2, 0]]]]}, "loop_count": {}, "top_n": [], "num_stitched": 20, "num_insts": 20, "websocket_port": 18000, "generation_time": "Wed May 28 09:55:56 2025"}